togglee/__init__.py
togglee/togglee.py
togglee/helpers/__init__.py
togglee/helpers/mappers.py
togglee/strategies/__init__.py
togglee/strategies/context.py
togglee/strategies/main.py
togglee/strategies/release.py
togglee-1.0.48.dist-info/LICENSE
togglee-1.0.48.dist-info/METADATA
togglee-1.0.48.dist-info/WHEEL
togglee-1.0.48.dist-info/top_level.txt
togglee-1.0.48.dist-info/RECORD
