Metadata-Version: 2.1
Name: togglee
Version: 1.0.48
Summary: Simple toggles for python from a url reference
Home-page: https://github.com/togglee/togglee-python
Author: kanekotic
Author-email: me@kanekotic.com
License: Apache-2.0
Platform: UNKNOWN
Requires-Dist: requests (>=2)
